{
   "SetViewMode":"55",
   "channels":[
      {
         "name":"[COLOR yellow]2021-04-18 23:00 Calcio[\/COLOR] [COLOR lime]Independiente Defensa y Justicia[\/COLOR]",
         "thumbnail":"https:\/\/media.diariorepublica.com\/cms\/wp-content\/uploads\/2015\/03\/roja.png",
         "fanart":"https:\/\/www.stadiotardini.it\/wp-content\/uploads\/2016\/12\/mandrakata.jpg",
         "info":"No info",
         "items":[
            {
               "title":"[COLOR lime]EXTREMO TV Play[\/COLOR] [COLOR aqua](Web (flash))[\/COLOR]",
               "link":"https:\/\/www.extremotvplay.com\/tnt-sports-en-vivo.php",
               "thumbnail":"https:\/\/media.diariorepublica.com\/cms\/wp-content\/uploads\/2015\/03\/roja.png",
               "fanart":"https:\/\/www.stadiotardini.it\/wp-content\/uploads\/2016\/12\/mandrakata.jpg",
               "info":"No info"
            },
            {
               "title":"[COLOR lime]EXTREMO TV Play[\/COLOR] [COLOR aqua](Web (flash))[\/COLOR]",
               "link":"https:\/\/www.extremotvplay.com\/1804\/link-3.php",
               "thumbnail":"https:\/\/media.diariorepublica.com\/cms\/wp-content\/uploads\/2015\/03\/roja.png",
               "fanart":"https:\/\/www.stadiotardini.it\/wp-content\/uploads\/2016\/12\/mandrakata.jpg",
               "info":"No info"
            },
            {
               "title":"[COLOR lime]EXTREMO TV Play[\/COLOR] [COLOR aqua](Web (flash))[\/COLOR]",
               "link":"https:\/\/www.extremotvplay.com\/1804\/link-5.php",
               "thumbnail":"https:\/\/media.diariorepublica.com\/cms\/wp-content\/uploads\/2015\/03\/roja.png",
               "fanart":"https:\/\/www.stadiotardini.it\/wp-content\/uploads\/2016\/12\/mandrakata.jpg",
               "info":"No info"
            },
            {
               "title":"[COLOR lime]Rivo PSNTV 11[\/COLOR] [COLOR aqua](Web (flash))[\/COLOR]",
               "link":"http:\/\/to.xrivonet.info\/11c.html#w",
               "thumbnail":"https:\/\/media.diariorepublica.com\/cms\/wp-content\/uploads\/2015\/03\/roja.png",
               "fanart":"https:\/\/www.stadiotardini.it\/wp-content\/uploads\/2016\/12\/mandrakata.jpg",
               "info":"No info"
            },
            {
               "title":"[COLOR lime]Rivo PSNTV 12[\/COLOR] [COLOR aqua](Web (flash))[\/COLOR]",
               "link":"http:\/\/to.xrivonet.info\/11c.html#k3",
               "thumbnail":"https:\/\/media.diariorepublica.com\/cms\/wp-content\/uploads\/2015\/03\/roja.png",
               "fanart":"https:\/\/www.stadiotardini.it\/wp-content\/uploads\/2016\/12\/mandrakata.jpg",
               "info":"No info"
            },
            {
               "title":"[COLOR lime]Sebn 31[\/COLOR] [COLOR aqua](Web (flash))[\/COLOR]",
               "link":"http:\/\/sebnsc.club\/180421\/sebn-31.html",
               "thumbnail":"https:\/\/media.diariorepublica.com\/cms\/wp-content\/uploads\/2015\/03\/roja.png",
               "fanart":"https:\/\/www.stadiotardini.it\/wp-content\/uploads\/2016\/12\/mandrakata.jpg",
               "info":"No info"
            },
            {
               "title":"[COLOR lime]Game Changer[\/COLOR] [COLOR aqua](Webflash)[\/COLOR]",
               "link":"https:\/\/datingpeople.xyz\/dating\/m65.php",
               "thumbnail":"https:\/\/media.diariorepublica.com\/cms\/wp-content\/uploads\/2015\/03\/roja.png",
               "fanart":"https:\/\/www.stadiotardini.it\/wp-content\/uploads\/2016\/12\/mandrakata.jpg",
               "info":"No info"
            },
            {
               "title":"[COLOR lime]My Soccer TV[\/COLOR] [COLOR aqua](Mobile + web flash)[\/COLOR]",
               "link":"https:\/\/mysoccertv.xyz\/ch\/65.php",
               "thumbnail":"https:\/\/media.diariorepublica.com\/cms\/wp-content\/uploads\/2015\/03\/roja.png",
               "fanart":"https:\/\/www.stadiotardini.it\/wp-content\/uploads\/2016\/12\/mandrakata.jpg",
               "info":"No info"
            },
            {
               "title":"[COLOR lime]Lovelystreamer[\/COLOR] [COLOR aqua](Mobile+web flash)[\/COLOR]",
               "link":"https:\/\/extremotvplay.xyz\/18\/Independiente-Defensa-es.php",
               "thumbnail":"https:\/\/media.diariorepublica.com\/cms\/wp-content\/uploads\/2015\/03\/roja.png",
               "fanart":"https:\/\/www.stadiotardini.it\/wp-content\/uploads\/2016\/12\/mandrakata.jpg",
               "info":"No info"
            },
            {
               "title":"[COLOR lime]P2P Sports[\/COLOR] [COLOR aqua](Web flash + mobile)[\/COLOR]",
               "link":"https:\/\/hikingfly.com\/hiking\/m65.php",
               "thumbnail":"https:\/\/media.diariorepublica.com\/cms\/wp-content\/uploads\/2015\/03\/roja.png",
               "fanart":"https:\/\/www.stadiotardini.it\/wp-content\/uploads\/2016\/12\/mandrakata.jpg",
               "info":"No info"
            },
            {
               "title":"[COLOR lime]CR7 Soccer[\/COLOR] [COLOR aqua](Web flash)[\/COLOR]",
               "link":"https:\/\/cr7soccer.club\/1004\/M65.php",
               "thumbnail":"https:\/\/media.diariorepublica.com\/cms\/wp-content\/uploads\/2015\/03\/roja.png",
               "fanart":"https:\/\/www.stadiotardini.it\/wp-content\/uploads\/2016\/12\/mandrakata.jpg",
               "info":"No info"
            },
            {
               "title":"[COLOR lime]Athletic Sports[\/COLOR] [COLOR aqua](Web flash)[\/COLOR]",
               "link":"https:\/\/zakkstream.online\/Soccer\/m65.php",
               "thumbnail":"https:\/\/media.diariorepublica.com\/cms\/wp-content\/uploads\/2015\/03\/roja.png",
               "fanart":"https:\/\/www.stadiotardini.it\/wp-content\/uploads\/2016\/12\/mandrakata.jpg",
               "info":"No info"
            },
            {
               "title":"[COLOR lime]Techmaza[\/COLOR] [COLOR aqua](Web flash)[\/COLOR]",
               "link":"https:\/\/techmaza.club\/T15\/65.php",
               "thumbnail":"https:\/\/media.diariorepublica.com\/cms\/wp-content\/uploads\/2015\/03\/roja.png",
               "fanart":"https:\/\/www.stadiotardini.it\/wp-content\/uploads\/2016\/12\/mandrakata.jpg",
               "info":"No info"
            },
            {
               "title":"[COLOR lime]britannysports[\/COLOR] [COLOR aqua](Mobile + web flash)[\/COLOR]",
               "link":"https:\/\/britannysports.xyz\/streamb\/65.php",
               "thumbnail":"https:\/\/media.diariorepublica.com\/cms\/wp-content\/uploads\/2015\/03\/roja.png",
               "fanart":"https:\/\/www.stadiotardini.it\/wp-content\/uploads\/2016\/12\/mandrakata.jpg",
               "info":"No info"
            },
            {
               "title":"[COLOR lime]allstd[\/COLOR] [COLOR aqua](Web (flash))[\/COLOR]",
               "link":"http:\/\/actusports.eu\/live\/?ch=13&streaming=Independiente-vs-Defensa-y-Justicia",
               "thumbnail":"https:\/\/media.diariorepublica.com\/cms\/wp-content\/uploads\/2015\/03\/roja.png",
               "fanart":"https:\/\/www.stadiotardini.it\/wp-content\/uploads\/2016\/12\/mandrakata.jpg",
               "info":"No info"
            },
            {
               "title":"[COLOR lime]polyall[\/COLOR] [COLOR aqua](Web flash)[\/COLOR]",
               "link":"http:\/\/polysportstv.info\/live\/?ch=13&streaming=Independiente-vs-Defensa-y-Justicia",
               "thumbnail":"https:\/\/media.diariorepublica.com\/cms\/wp-content\/uploads\/2015\/03\/roja.png",
               "fanart":"https:\/\/www.stadiotardini.it\/wp-content\/uploads\/2016\/12\/mandrakata.jpg",
               "info":"No info"
            }
         ]
      },
      {
         "name":"[COLOR yellow]2021-04-18 23:15 Calcio[\/COLOR] [COLOR lime]Real New York FC New York Contour Utd[\/COLOR]",
         "thumbnail":"https:\/\/media.diariorepublica.com\/cms\/wp-content\/uploads\/2015\/03\/roja.png",
         "fanart":"https:\/\/www.stadiotardini.it\/wp-content\/uploads\/2016\/12\/mandrakata.jpg",
         "info":"No info",
         "items":[
            {
               "title":"[COLOR lime]Real New York[\/COLOR] [COLOR aqua](Mycujoo)[\/COLOR]",
               "link":"https:\/\/mycujoo.tv\/en\/view\/event\/cknlddkombize0hacvqoophbq",
               "thumbnail":"https:\/\/media.diariorepublica.com\/cms\/wp-content\/uploads\/2015\/03\/roja.png",
               "fanart":"https:\/\/www.stadiotardini.it\/wp-content\/uploads\/2016\/12\/mandrakata.jpg",
               "info":"No info"
            }
         ]
      },
      {
         "name":"[COLOR yellow]2021-04-18 23:30 Calcio[\/COLOR] [COLOR lime]Columbus Crew Philadelphia Union[\/COLOR]",
         "thumbnail":"https:\/\/media.diariorepublica.com\/cms\/wp-content\/uploads\/2015\/03\/roja.png",
         "fanart":"https:\/\/www.stadiotardini.it\/wp-content\/uploads\/2016\/12\/mandrakata.jpg",
         "info":"No info",
         "items":[
            {
               "title":"[COLOR lime]FutbolbogANDRES HQ[\/COLOR] [COLOR aqua](Livestream)[\/COLOR]",
               "link":"https:\/\/www.vivoplay.sigue.la\/p\/spo-1.html",
               "thumbnail":"https:\/\/media.diariorepublica.com\/cms\/wp-content\/uploads\/2015\/03\/roja.png",
               "fanart":"https:\/\/www.stadiotardini.it\/wp-content\/uploads\/2016\/12\/mandrakata.jpg",
               "info":"No info"
            },
            {
               "title":"[COLOR lime]EXTREMO TV Play[\/COLOR] [COLOR aqua](Web (flash))[\/COLOR]",
               "link":"https:\/\/www.extremotvplay.com\/1804\/link-41.php",
               "thumbnail":"https:\/\/media.diariorepublica.com\/cms\/wp-content\/uploads\/2015\/03\/roja.png",
               "fanart":"https:\/\/www.stadiotardini.it\/wp-content\/uploads\/2016\/12\/mandrakata.jpg",
               "info":"No info"
            },
            {
               "title":"[COLOR lime]EXTREMO TV Play[\/COLOR] [COLOR aqua](Web (flash))[\/COLOR]",
               "link":"https:\/\/www.extremotvplay.com\/1804\/link-42.php",
               "thumbnail":"https:\/\/media.diariorepublica.com\/cms\/wp-content\/uploads\/2015\/03\/roja.png",
               "fanart":"https:\/\/www.stadiotardini.it\/wp-content\/uploads\/2016\/12\/mandrakata.jpg",
               "info":"No info"
            },
            {
               "title":"[COLOR lime]Sebn 29[\/COLOR] [COLOR aqua](Web (flash))[\/COLOR]",
               "link":"http:\/\/sebnsc.club\/180421\/sebn-29.html",
               "thumbnail":"https:\/\/media.diariorepublica.com\/cms\/wp-content\/uploads\/2015\/03\/roja.png",
               "fanart":"https:\/\/www.stadiotardini.it\/wp-content\/uploads\/2016\/12\/mandrakata.jpg",
               "info":"No info"
            },
            {
               "title":"[COLOR lime]ArenaVision 36[\/COLOR] [COLOR aqua](Acestream ( web ))[\/COLOR]",
               "link":"https:\/\/arenavision.club\/36?fwdscyuhe6w7dfvgfedc",
               "thumbnail":"https:\/\/media.diariorepublica.com\/cms\/wp-content\/uploads\/2015\/03\/roja.png",
               "fanart":"https:\/\/www.stadiotardini.it\/wp-content\/uploads\/2016\/12\/mandrakata.jpg",
               "info":"No info"
            },
            {
               "title":"[COLOR lime]streamsport[\/COLOR] [COLOR aqua](Webflash)[\/COLOR]",
               "link":"http:\/\/streamsport.pro\/live\/s13.php",
               "thumbnail":"https:\/\/media.diariorepublica.com\/cms\/wp-content\/uploads\/2015\/03\/roja.png",
               "fanart":"https:\/\/www.stadiotardini.it\/wp-content\/uploads\/2016\/12\/mandrakata.jpg",
               "info":"No info"
            },
            {
               "title":"[COLOR lime]streamsport[\/COLOR] [COLOR aqua](Webflash)[\/COLOR]",
               "link":"http:\/\/streamsport.pro\/live\/s19.php",
               "thumbnail":"https:\/\/media.diariorepublica.com\/cms\/wp-content\/uploads\/2015\/03\/roja.png",
               "fanart":"https:\/\/www.stadiotardini.it\/wp-content\/uploads\/2016\/12\/mandrakata.jpg",
               "info":"No info"
            },
            {
               "title":"[COLOR lime]My Soccer TV[\/COLOR] [COLOR aqua](Mobile + web flash)[\/COLOR]",
               "link":"https:\/\/mysoccertv.xyz\/ch\/22.php",
               "thumbnail":"https:\/\/media.diariorepublica.com\/cms\/wp-content\/uploads\/2015\/03\/roja.png",
               "fanart":"https:\/\/www.stadiotardini.it\/wp-content\/uploads\/2016\/12\/mandrakata.jpg",
               "info":"No info"
            },
            {
               "title":"[COLOR lime]My Soccer TV[\/COLOR] [COLOR aqua](Mobile + web flash)[\/COLOR]",
               "link":"https:\/\/mysoccertv.xyz\/sp\/p3.php",
               "thumbnail":"https:\/\/media.diariorepublica.com\/cms\/wp-content\/uploads\/2015\/03\/roja.png",
               "fanart":"https:\/\/www.stadiotardini.it\/wp-content\/uploads\/2016\/12\/mandrakata.jpg",
               "info":"No info"
            },
            {
               "title":"[COLOR lime]Lovelystreamer[\/COLOR] [COLOR aqua](Mobile+web flash)[\/COLOR]",
               "link":"https:\/\/extremotvplay.xyz\/18\/Columbus-Philadelphia-es.php",
               "thumbnail":"https:\/\/media.diariorepublica.com\/cms\/wp-content\/uploads\/2015\/03\/roja.png",
               "fanart":"https:\/\/www.stadiotardini.it\/wp-content\/uploads\/2016\/12\/mandrakata.jpg",
               "info":"No info"
            },
            {
               "title":"[COLOR lime]CR7 Soccer[\/COLOR] [COLOR aqua](Web flash)[\/COLOR]",
               "link":"https:\/\/cr7soccer.club\/1004\/1.php",
               "thumbnail":"https:\/\/media.diariorepublica.com\/cms\/wp-content\/uploads\/2015\/03\/roja.png",
               "fanart":"https:\/\/www.stadiotardini.it\/wp-content\/uploads\/2016\/12\/mandrakata.jpg",
               "info":"No info"
            },
            {
               "title":"[COLOR lime]Techmaza[\/COLOR] [COLOR aqua](Web flash)[\/COLOR]",
               "link":"https:\/\/techmaza.club\/T15\/22.php",
               "thumbnail":"https:\/\/media.diariorepublica.com\/cms\/wp-content\/uploads\/2015\/03\/roja.png",
               "fanart":"https:\/\/www.stadiotardini.it\/wp-content\/uploads\/2016\/12\/mandrakata.jpg",
               "info":"No info"
            },
            {
               "title":"[COLOR lime]britannysports[\/COLOR] [COLOR aqua](Mobile + web flash)[\/COLOR]",
               "link":"https:\/\/britannysports.xyz\/streama\/pp3.php",
               "thumbnail":"https:\/\/media.diariorepublica.com\/cms\/wp-content\/uploads\/2015\/03\/roja.png",
               "fanart":"https:\/\/www.stadiotardini.it\/wp-content\/uploads\/2016\/12\/mandrakata.jpg",
               "info":"No info"
            },
            {
               "title":"[COLOR lime]britannysports[\/COLOR] [COLOR aqua](Mobile + web flash)[\/COLOR]",
               "link":"https:\/\/britannysports.xyz\/streamb\/22.php",
               "thumbnail":"https:\/\/media.diariorepublica.com\/cms\/wp-content\/uploads\/2015\/03\/roja.png",
               "fanart":"https:\/\/www.stadiotardini.it\/wp-content\/uploads\/2016\/12\/mandrakata.jpg",
               "info":"No info"
            },
            {
               "title":"[COLOR lime]ZonaSports[\/COLOR] [COLOR aqua](Web(flash))[\/COLOR]",
               "link":"http:\/\/zonasports.xyz\/aa\/hh1.php",
               "thumbnail":"https:\/\/media.diariorepublica.com\/cms\/wp-content\/uploads\/2015\/03\/roja.png",
               "fanart":"https:\/\/www.stadiotardini.it\/wp-content\/uploads\/2016\/12\/mandrakata.jpg",
               "info":"No info"
            },
            {
               "title":"[COLOR lime]ttStreams[\/COLOR] [COLOR aqua](Web(flash))[\/COLOR]",
               "link":"http:\/\/ttstreams.xyz\/sxsx\/h1.php",
               "thumbnail":"https:\/\/media.diariorepublica.com\/cms\/wp-content\/uploads\/2015\/03\/roja.png",
               "fanart":"https:\/\/www.stadiotardini.it\/wp-content\/uploads\/2016\/12\/mandrakata.jpg",
               "info":"No info"
            },
            {
               "title":"[COLOR lime]DhdSports[\/COLOR] [COLOR aqua](All devices)[\/COLOR]",
               "link":"http:\/\/zonasports.xyz\/aa\/ss3.php",
               "thumbnail":"https:\/\/media.diariorepublica.com\/cms\/wp-content\/uploads\/2015\/03\/roja.png",
               "fanart":"https:\/\/www.stadiotardini.it\/wp-content\/uploads\/2016\/12\/mandrakata.jpg",
               "info":"No info"
            },
            {
               "title":"[COLOR lime]CNSports[\/COLOR] [COLOR aqua](All devices)[\/COLOR]",
               "link":"http:\/\/ttstreams.xyz\/sxsx\/s3.php",
               "thumbnail":"https:\/\/media.diariorepublica.com\/cms\/wp-content\/uploads\/2015\/03\/roja.png",
               "fanart":"https:\/\/www.stadiotardini.it\/wp-content\/uploads\/2016\/12\/mandrakata.jpg",
               "info":"No info"
            },
            {
               "title":"[COLOR lime]TotalSports[\/COLOR] [COLOR aqua](Web(flash))[\/COLOR]",
               "link":"http:\/\/totalhdsport.club\/online\/h1.php",
               "thumbnail":"https:\/\/media.diariorepublica.com\/cms\/wp-content\/uploads\/2015\/03\/roja.png",
               "fanart":"https:\/\/www.stadiotardini.it\/wp-content\/uploads\/2016\/12\/mandrakata.jpg",
               "info":"No info"
            },
            {
               "title":"[COLOR lime]nflhighlights[\/COLOR] [COLOR aqua](Web(flash))[\/COLOR]",
               "link":"https:\/\/nflhighlights.xyz\/sportz\/hd1.php",
               "thumbnail":"https:\/\/media.diariorepublica.com\/cms\/wp-content\/uploads\/2015\/03\/roja.png",
               "fanart":"https:\/\/www.stadiotardini.it\/wp-content\/uploads\/2016\/12\/mandrakata.jpg",
               "info":"No info"
            },
            {
               "title":"[COLOR lime]nbahighlights[\/COLOR] [COLOR aqua](Web(flash))[\/COLOR]",
               "link":"https:\/\/nbahighlights.xyz\/sportz\/hd1.php",
               "thumbnail":"https:\/\/media.diariorepublica.com\/cms\/wp-content\/uploads\/2015\/03\/roja.png",
               "fanart":"https:\/\/www.stadiotardini.it\/wp-content\/uploads\/2016\/12\/mandrakata.jpg",
               "info":"No info"
            },
            {
               "title":"[COLOR lime]polyall[\/COLOR] [COLOR aqua](Web flash)[\/COLOR]",
               "link":"http:\/\/polysportstv.info\/live\/?ch=21&streaming=Columbus-Crew-vs-Philadelphia-Union",
               "thumbnail":"https:\/\/media.diariorepublica.com\/cms\/wp-content\/uploads\/2015\/03\/roja.png",
               "fanart":"https:\/\/www.stadiotardini.it\/wp-content\/uploads\/2016\/12\/mandrakata.jpg",
               "info":"No info"
            },
            {
               "title":"[COLOR lime]polyall[\/COLOR] [COLOR aqua](Web flash)[\/COLOR]",
               "link":"http:\/\/polysportstv.info\/live\/?ch=43&streaming=Columbus-Crew-vs-Philadelphia-Union",
               "thumbnail":"https:\/\/media.diariorepublica.com\/cms\/wp-content\/uploads\/2015\/03\/roja.png",
               "fanart":"https:\/\/www.stadiotardini.it\/wp-content\/uploads\/2016\/12\/mandrakata.jpg",
               "info":"No info"
            }
         ]
      },
      {
         "name":"[COLOR yellow]2021-04-18 23:30 Calcio[\/COLOR] [COLOR lime]MBCF Academy Florida Soccer Soldiers 2[\/COLOR]",
         "thumbnail":"https:\/\/media.diariorepublica.com\/cms\/wp-content\/uploads\/2015\/03\/roja.png",
         "fanart":"https:\/\/www.stadiotardini.it\/wp-content\/uploads\/2016\/12\/mandrakata.jpg",
         "info":"No info",
         "items":[
            {
               "title":"[COLOR lime]Veter Media[\/COLOR] [COLOR aqua](Mycujoo)[\/COLOR]",
               "link":"https:\/\/mycujoo.tv\/en\/view\/event\/cknji0aceap3r0hacq7bb75pv",
               "thumbnail":"https:\/\/media.diariorepublica.com\/cms\/wp-content\/uploads\/2015\/03\/roja.png",
               "fanart":"https:\/\/www.stadiotardini.it\/wp-content\/uploads\/2016\/12\/mandrakata.jpg",
               "info":"No info"
            }
         ]
      },
      {
         "name":"[COLOR yellow]2021-04-19 00:15 Calcio[\/COLOR] [COLOR lime]Chinandega FC CD Junior[\/COLOR]",
         "thumbnail":"https:\/\/media.diariorepublica.com\/cms\/wp-content\/uploads\/2015\/03\/roja.png",
         "fanart":"https:\/\/www.stadiotardini.it\/wp-content\/uploads\/2016\/12\/mandrakata.jpg",
         "info":"No info",
         "items":[
            {
               "title":"[COLOR lime]Liga Primera[\/COLOR] [COLOR aqua](Youtube --)[\/COLOR]",
               "link":"https:\/\/www.youtube-nocookie.com\/embed\/e1-O_a9tUc0?autoplay=1",
               "thumbnail":"https:\/\/media.diariorepublica.com\/cms\/wp-content\/uploads\/2015\/03\/roja.png",
               "fanart":"https:\/\/www.stadiotardini.it\/wp-content\/uploads\/2016\/12\/mandrakata.jpg",
               "info":"No info"
            }
         ]
      },
      {
         "name":"[COLOR yellow]2021-04-19 01:00 Calcio[\/COLOR] [COLOR lime]Emelec Tecnico[\/COLOR]",
         "thumbnail":"https:\/\/media.diariorepublica.com\/cms\/wp-content\/uploads\/2015\/03\/roja.png",
         "fanart":"https:\/\/www.stadiotardini.it\/wp-content\/uploads\/2016\/12\/mandrakata.jpg",
         "info":"No info",
         "items":[
            {
               "title":"[COLOR lime]FutbolbogANDRES HQ[\/COLOR] [COLOR aqua](Livestream)[\/COLOR]",
               "link":"https:\/\/www.vivoplay.sigue.la\/p\/bx-16.html",
               "thumbnail":"https:\/\/media.diariorepublica.com\/cms\/wp-content\/uploads\/2015\/03\/roja.png",
               "fanart":"https:\/\/www.stadiotardini.it\/wp-content\/uploads\/2016\/12\/mandrakata.jpg",
               "info":"No info"
            },
            {
               "title":"[COLOR lime]FutbolbogANDRES HQ[\/COLOR] [COLOR aqua](Livestream)[\/COLOR]",
               "link":"https:\/\/www.vivoplay.sigue.la\/p\/bx-17.html",
               "thumbnail":"https:\/\/media.diariorepublica.com\/cms\/wp-content\/uploads\/2015\/03\/roja.png",
               "fanart":"https:\/\/www.stadiotardini.it\/wp-content\/uploads\/2016\/12\/mandrakata.jpg",
               "info":"No info"
            },
            {
               "title":"[COLOR lime]FutbolbogANDRES HQ[\/COLOR] [COLOR aqua](Livestream)[\/COLOR]",
               "link":"https:\/\/www.vivoplay.sigue.la\/p\/bx-18.html",
               "thumbnail":"https:\/\/media.diariorepublica.com\/cms\/wp-content\/uploads\/2015\/03\/roja.png",
               "fanart":"https:\/\/www.stadiotardini.it\/wp-content\/uploads\/2016\/12\/mandrakata.jpg",
               "info":"No info"
            },
            {
               "title":"[COLOR lime]Rivo PSNTV 12[\/COLOR] [COLOR aqua](Web (flash))[\/COLOR]",
               "link":"http:\/\/to.xrivonet.info\/12b.html#w",
               "thumbnail":"https:\/\/media.diariorepublica.com\/cms\/wp-content\/uploads\/2015\/03\/roja.png",
               "fanart":"https:\/\/www.stadiotardini.it\/wp-content\/uploads\/2016\/12\/mandrakata.jpg",
               "info":"No info"
            },
            {
               "title":"[COLOR lime]Sebn 32[\/COLOR] [COLOR aqua](Web (flash))[\/COLOR]",
               "link":"http:\/\/sebnsc.club\/180421\/sebn-32.html",
               "thumbnail":"https:\/\/media.diariorepublica.com\/cms\/wp-content\/uploads\/2015\/03\/roja.png",
               "fanart":"https:\/\/www.stadiotardini.it\/wp-content\/uploads\/2016\/12\/mandrakata.jpg",
               "info":"No info"
            },
            {
               "title":"[COLOR lime]My Soccer TV[\/COLOR] [COLOR aqua](Mobile + web flash)[\/COLOR]",
               "link":"https:\/\/mysoccertv.xyz\/ch\/69.php",
               "thumbnail":"https:\/\/media.diariorepublica.com\/cms\/wp-content\/uploads\/2015\/03\/roja.png",
               "fanart":"https:\/\/www.stadiotardini.it\/wp-content\/uploads\/2016\/12\/mandrakata.jpg",
               "info":"No info"
            },
            {
               "title":"[COLOR lime]Lovelystreamer[\/COLOR] [COLOR aqua](Mobile+web flash)[\/COLOR]",
               "link":"https:\/\/extremotvplay.xyz\/18\/Emelec-Tecnicop-es.php",
               "thumbnail":"https:\/\/media.diariorepublica.com\/cms\/wp-content\/uploads\/2015\/03\/roja.png",
               "fanart":"https:\/\/www.stadiotardini.it\/wp-content\/uploads\/2016\/12\/mandrakata.jpg",
               "info":"No info"
            },
            {
               "title":"[COLOR lime]P2P Sports[\/COLOR] [COLOR aqua](Web flash + mobile)[\/COLOR]",
               "link":"https:\/\/hikingfly.com\/hiking\/m69.php",
               "thumbnail":"https:\/\/media.diariorepublica.com\/cms\/wp-content\/uploads\/2015\/03\/roja.png",
               "fanart":"https:\/\/www.stadiotardini.it\/wp-content\/uploads\/2016\/12\/mandrakata.jpg",
               "info":"No info"
            },
            {
               "title":"[COLOR lime]CR7 Soccer[\/COLOR] [COLOR aqua](Web flash)[\/COLOR]",
               "link":"https:\/\/cr7soccer.club\/1004\/M69.php",
               "thumbnail":"https:\/\/media.diariorepublica.com\/cms\/wp-content\/uploads\/2015\/03\/roja.png",
               "fanart":"https:\/\/www.stadiotardini.it\/wp-content\/uploads\/2016\/12\/mandrakata.jpg",
               "info":"No info"
            },
            {
               "title":"[COLOR lime]Athletic Sports[\/COLOR] [COLOR aqua](Web flash)[\/COLOR]",
               "link":"https:\/\/zakkstream.online\/Soccer\/m69.php",
               "thumbnail":"https:\/\/media.diariorepublica.com\/cms\/wp-content\/uploads\/2015\/03\/roja.png",
               "fanart":"https:\/\/www.stadiotardini.it\/wp-content\/uploads\/2016\/12\/mandrakata.jpg",
               "info":"No info"
            },
            {
               "title":"[COLOR lime]Techmaza[\/COLOR] [COLOR aqua](Web flash)[\/COLOR]",
               "link":"https:\/\/techmaza.club\/T15\/69.php",
               "thumbnail":"https:\/\/media.diariorepublica.com\/cms\/wp-content\/uploads\/2015\/03\/roja.png",
               "fanart":"https:\/\/www.stadiotardini.it\/wp-content\/uploads\/2016\/12\/mandrakata.jpg",
               "info":"No info"
            },
            {
               "title":"[COLOR lime]britannysports[\/COLOR] [COLOR aqua](Mobile + web flash)[\/COLOR]",
               "link":"https:\/\/britannysports.xyz\/streamb\/69.php",
               "thumbnail":"https:\/\/media.diariorepublica.com\/cms\/wp-content\/uploads\/2015\/03\/roja.png",
               "fanart":"https:\/\/www.stadiotardini.it\/wp-content\/uploads\/2016\/12\/mandrakata.jpg",
               "info":"No info"
            },
            {
               "title":"[COLOR lime]TotalSports[\/COLOR] [COLOR aqua](Web(flash))[\/COLOR]",
               "link":"http:\/\/totalhdsport.club\/street\/stream32.php",
               "thumbnail":"https:\/\/media.diariorepublica.com\/cms\/wp-content\/uploads\/2015\/03\/roja.png",
               "fanart":"https:\/\/www.stadiotardini.it\/wp-content\/uploads\/2016\/12\/mandrakata.jpg",
               "info":"No info"
            },
            {
               "title":"[COLOR lime]FutbolStream[\/COLOR] [COLOR aqua](All devices)[\/COLOR]",
               "link":"http:\/\/footballstream.pw\/trumm\/st32.php",
               "thumbnail":"https:\/\/media.diariorepublica.com\/cms\/wp-content\/uploads\/2015\/03\/roja.png",
               "fanart":"https:\/\/www.stadiotardini.it\/wp-content\/uploads\/2016\/12\/mandrakata.jpg",
               "info":"No info"
            },
            {
               "title":"[COLOR lime]ZonaSports[\/COLOR] [COLOR aqua](Web(flash))[\/COLOR]",
               "link":"http:\/\/zonasports.xyz\/troga\/stream31.php",
               "thumbnail":"https:\/\/media.diariorepublica.com\/cms\/wp-content\/uploads\/2015\/03\/roja.png",
               "fanart":"https:\/\/www.stadiotardini.it\/wp-content\/uploads\/2016\/12\/mandrakata.jpg",
               "info":"No info"
            },
            {
               "title":"[COLOR lime]datvEcuador[\/COLOR] [COLOR aqua](Web (flash))[\/COLOR]",
               "link":"https:\/\/dalive.nl\/c4.php",
               "thumbnail":"https:\/\/media.diariorepublica.com\/cms\/wp-content\/uploads\/2015\/03\/roja.png",
               "fanart":"https:\/\/www.stadiotardini.it\/wp-content\/uploads\/2016\/12\/mandrakata.jpg",
               "info":"No info"
            }
         ]
      },
      {
         "name":"[COLOR yellow]2021-04-19 01:00 Basket[\/COLOR] [COLOR lime]Hornets Trail Blazers[\/COLOR]",
         "thumbnail":"https:\/\/media.diariorepublica.com\/cms\/wp-content\/uploads\/2015\/03\/roja.png",
         "fanart":"https:\/\/www.stadiotardini.it\/wp-content\/uploads\/2016\/12\/mandrakata.jpg",
         "info":"No info",
         "items":[
            {
               "title":"[COLOR lime]FutbolbogANDRES HQ[\/COLOR] [COLOR aqua](Livestream)[\/COLOR]",
               "link":"https:\/\/www.vivoplay.sigue.la\/p\/bx-1.html",
               "thumbnail":"https:\/\/media.diariorepublica.com\/cms\/wp-content\/uploads\/2015\/03\/roja.png",
               "fanart":"https:\/\/www.stadiotardini.it\/wp-content\/uploads\/2016\/12\/mandrakata.jpg",
               "info":"No info"
            },
            {
               "title":"[COLOR lime]Rivo TVSPORTS 2[\/COLOR] [COLOR aqua](Web (flash))[\/COLOR]",
               "link":"http:\/\/to.xrivonet.info\/2c.html#w",
               "thumbnail":"https:\/\/media.diariorepublica.com\/cms\/wp-content\/uploads\/2015\/03\/roja.png",
               "fanart":"https:\/\/www.stadiotardini.it\/wp-content\/uploads\/2016\/12\/mandrakata.jpg",
               "info":"No info"
            },
            {
               "title":"[COLOR lime]Sebn 11[\/COLOR] [COLOR aqua](Web (flash))[\/COLOR]",
               "link":"http:\/\/sebnsc.club\/180421\/sebn-11.html",
               "thumbnail":"https:\/\/media.diariorepublica.com\/cms\/wp-content\/uploads\/2015\/03\/roja.png",
               "fanart":"https:\/\/www.stadiotardini.it\/wp-content\/uploads\/2016\/12\/mandrakata.jpg",
               "info":"No info"
            },
            {
               "title":"[COLOR lime]My Soccer TV[\/COLOR] [COLOR aqua](Mobile + web flash)[\/COLOR]",
               "link":"https:\/\/mysoccertv.xyz\/ch\/41.php",
               "thumbnail":"https:\/\/media.diariorepublica.com\/cms\/wp-content\/uploads\/2015\/03\/roja.png",
               "fanart":"https:\/\/www.stadiotardini.it\/wp-content\/uploads\/2016\/12\/mandrakata.jpg",
               "info":"No info"
            },
            {
               "title":"[COLOR lime]Lovelystreamer[\/COLOR] [COLOR aqua](Mobile+web flash)[\/COLOR]",
               "link":"https:\/\/extremotvplay.xyz\/18\/NBA-Hornets-Blazers.php",
               "thumbnail":"https:\/\/media.diariorepublica.com\/cms\/wp-content\/uploads\/2015\/03\/roja.png",
               "fanart":"https:\/\/www.stadiotardini.it\/wp-content\/uploads\/2016\/12\/mandrakata.jpg",
               "info":"No info"
            },
            {
               "title":"[COLOR lime]TotalSports[\/COLOR] [COLOR aqua](All devices)[\/COLOR]",
               "link":"http:\/\/totalhdsport.club\/street\/stream11.php",
               "thumbnail":"https:\/\/media.diariorepublica.com\/cms\/wp-content\/uploads\/2015\/03\/roja.png",
               "fanart":"https:\/\/www.stadiotardini.it\/wp-content\/uploads\/2016\/12\/mandrakata.jpg",
               "info":"No info"
            },
            {
               "title":"[COLOR lime]FutbolStream[\/COLOR] [COLOR aqua](Mobile +web (flash))[\/COLOR]",
               "link":"http:\/\/footballstream.pw\/trumm\/st11.php",
               "thumbnail":"https:\/\/media.diariorepublica.com\/cms\/wp-content\/uploads\/2015\/03\/roja.png",
               "fanart":"https:\/\/www.stadiotardini.it\/wp-content\/uploads\/2016\/12\/mandrakata.jpg",
               "info":"No info"
            },
            {
               "title":"[COLOR lime]ZonaSports[\/COLOR] [COLOR aqua](All devices)[\/COLOR]",
               "link":"http:\/\/zonasports.xyz\/troga\/stream11.php",
               "thumbnail":"https:\/\/media.diariorepublica.com\/cms\/wp-content\/uploads\/2015\/03\/roja.png",
               "fanart":"https:\/\/www.stadiotardini.it\/wp-content\/uploads\/2016\/12\/mandrakata.jpg",
               "info":"No info"
            },
            {
               "title":"[COLOR lime]britannysports[\/COLOR] [COLOR aqua](Mobile + web flash)[\/COLOR]",
               "link":"https:\/\/britannysports.xyz\/streamb\/41.php",
               "thumbnail":"https:\/\/media.diariorepublica.com\/cms\/wp-content\/uploads\/2015\/03\/roja.png",
               "fanart":"https:\/\/www.stadiotardini.it\/wp-content\/uploads\/2016\/12\/mandrakata.jpg",
               "info":"No info"
            }
         ]
      },
      {
         "name":"[COLOR yellow]2021-04-19 01:00 Basket[\/COLOR] [COLOR lime]Magic Rockets[\/COLOR]",
         "thumbnail":"https:\/\/media.diariorepublica.com\/cms\/wp-content\/uploads\/2015\/03\/roja.png",
         "fanart":"https:\/\/www.stadiotardini.it\/wp-content\/uploads\/2016\/12\/mandrakata.jpg",
         "info":"No info",
         "items":[
            {
               "title":"[COLOR lime]FutbolbogANDRES HQ[\/COLOR] [COLOR aqua](Livestream)[\/COLOR]",
               "link":"https:\/\/www.vivoplay.sigue.la\/p\/bx-2.html",
               "thumbnail":"https:\/\/media.diariorepublica.com\/cms\/wp-content\/uploads\/2015\/03\/roja.png",
               "fanart":"https:\/\/www.stadiotardini.it\/wp-content\/uploads\/2016\/12\/mandrakata.jpg",
               "info":"No info"
            },
            {
               "title":"[COLOR lime]Rivo TVSPORTS 3[\/COLOR] [COLOR aqua](Web (flash))[\/COLOR]",
               "link":"http:\/\/to.xrivonet.info\/3c.html#w",
               "thumbnail":"https:\/\/media.diariorepublica.com\/cms\/wp-content\/uploads\/2015\/03\/roja.png",
               "fanart":"https:\/\/www.stadiotardini.it\/wp-content\/uploads\/2016\/12\/mandrakata.jpg",
               "info":"No info"
            },
            {
               "title":"[COLOR lime]Sebn 16[\/COLOR] [COLOR aqua](Web (flash))[\/COLOR]",
               "link":"http:\/\/sebnsc.club\/180421\/sebn-16.html",
               "thumbnail":"https:\/\/media.diariorepublica.com\/cms\/wp-content\/uploads\/2015\/03\/roja.png",
               "fanart":"https:\/\/www.stadiotardini.it\/wp-content\/uploads\/2016\/12\/mandrakata.jpg",
               "info":"No info"
            },
            {
               "title":"[COLOR lime]My Soccer TV[\/COLOR] [COLOR aqua](Mobile + web flash)[\/COLOR]",
               "link":"https:\/\/mysoccertv.xyz\/ch\/42.php",
               "thumbnail":"https:\/\/media.diariorepublica.com\/cms\/wp-content\/uploads\/2015\/03\/roja.png",
               "fanart":"https:\/\/www.stadiotardini.it\/wp-content\/uploads\/2016\/12\/mandrakata.jpg",
               "info":"No info"
            },
            {
               "title":"[COLOR lime]My Soccer TV[\/COLOR] [COLOR aqua](Mobile + web flash)[\/COLOR]",
               "link":"https:\/\/mysoccertv.xyz\/ch\/10.php",
               "thumbnail":"https:\/\/media.diariorepublica.com\/cms\/wp-content\/uploads\/2015\/03\/roja.png",
               "fanart":"https:\/\/www.stadiotardini.it\/wp-content\/uploads\/2016\/12\/mandrakata.jpg",
               "info":"No info"
            },
            {
               "title":"[COLOR lime]My Soccer TV[\/COLOR] [COLOR aqua](Mobile + web flash)[\/COLOR]",
               "link":"https:\/\/mysoccertv.xyz\/sp\/p5.php",
               "thumbnail":"https:\/\/media.diariorepublica.com\/cms\/wp-content\/uploads\/2015\/03\/roja.png",
               "fanart":"https:\/\/www.stadiotardini.it\/wp-content\/uploads\/2016\/12\/mandrakata.jpg",
               "info":"No info"
            },
            {
               "title":"[COLOR lime]Lovelystreamer[\/COLOR] [COLOR aqua](Mobile+web flash)[\/COLOR]",
               "link":"https:\/\/extremotvplay.xyz\/18\/NBA-Magic-Rockets-en.php",
               "thumbnail":"https:\/\/media.diariorepublica.com\/cms\/wp-content\/uploads\/2015\/03\/roja.png",
               "fanart":"https:\/\/www.stadiotardini.it\/wp-content\/uploads\/2016\/12\/mandrakata.jpg",
               "info":"No info"
            },
            {
               "title":"[COLOR lime]Extreme Streamer[\/COLOR] [COLOR aqua](Mobile+web flash)[\/COLOR]",
               "link":"https:\/\/extremotvplay.xyz\/18\/NBA-Magic-Rockets-fr.php",
               "thumbnail":"https:\/\/media.diariorepublica.com\/cms\/wp-content\/uploads\/2015\/03\/roja.png",
               "fanart":"https:\/\/www.stadiotardini.it\/wp-content\/uploads\/2016\/12\/mandrakata.jpg",
               "info":"No info"
            },
            {
               "title":"[COLOR lime]TotalSports[\/COLOR] [COLOR aqua](Web(flash))[\/COLOR]",
               "link":"http:\/\/totalhdsport.club\/street\/stream16.php",
               "thumbnail":"https:\/\/media.diariorepublica.com\/cms\/wp-content\/uploads\/2015\/03\/roja.png",
               "fanart":"https:\/\/www.stadiotardini.it\/wp-content\/uploads\/2016\/12\/mandrakata.jpg",
               "info":"No info"
            },
            {
               "title":"[COLOR lime]FutbolStream[\/COLOR] [COLOR aqua](All devices)[\/COLOR]",
               "link":"http:\/\/footballstream.pw\/trumm\/st16.php",
               "thumbnail":"https:\/\/media.diariorepublica.com\/cms\/wp-content\/uploads\/2015\/03\/roja.png",
               "fanart":"https:\/\/www.stadiotardini.it\/wp-content\/uploads\/2016\/12\/mandrakata.jpg",
               "info":"No info"
            },
            {
               "title":"[COLOR lime]ZonaSports[\/COLOR] [COLOR aqua](All devices)[\/COLOR]",
               "link":"http:\/\/zonasports.xyz\/troga\/stream16.php",
               "thumbnail":"https:\/\/media.diariorepublica.com\/cms\/wp-content\/uploads\/2015\/03\/roja.png",
               "fanart":"https:\/\/www.stadiotardini.it\/wp-content\/uploads\/2016\/12\/mandrakata.jpg",
               "info":"No info"
            },
            {
               "title":"[COLOR lime]britannysports[\/COLOR] [COLOR aqua](Mobile + web flash)[\/COLOR]",
               "link":"https:\/\/britannysports.xyz\/streamb\/42.php",
               "thumbnail":"https:\/\/media.diariorepublica.com\/cms\/wp-content\/uploads\/2015\/03\/roja.png",
               "fanart":"https:\/\/www.stadiotardini.it\/wp-content\/uploads\/2016\/12\/mandrakata.jpg",
               "info":"No info"
            },
            {
               "title":"[COLOR lime]britannysports[\/COLOR] [COLOR aqua](Mobile + web flash)[\/COLOR]",
               "link":"https:\/\/britannysports.xyz\/streamb\/10.php",
               "thumbnail":"https:\/\/media.diariorepublica.com\/cms\/wp-content\/uploads\/2015\/03\/roja.png",
               "fanart":"https:\/\/www.stadiotardini.it\/wp-content\/uploads\/2016\/12\/mandrakata.jpg",
               "info":"No info"
            },
            {
               "title":"[COLOR lime]britannysports[\/COLOR] [COLOR aqua](Mobile + web flash)[\/COLOR]",
               "link":"https:\/\/britannysports.xyz\/streama\/pp5.php",
               "thumbnail":"https:\/\/media.diariorepublica.com\/cms\/wp-content\/uploads\/2015\/03\/roja.png",
               "fanart":"https:\/\/www.stadiotardini.it\/wp-content\/uploads\/2016\/12\/mandrakata.jpg",
               "info":"No info"
            }
         ]
      },
      {
         "name":"[COLOR yellow]2021-04-19 01:00 Basket[\/COLOR] [COLOR lime]Raptors Thunder[\/COLOR]",
         "thumbnail":"https:\/\/media.diariorepublica.com\/cms\/wp-content\/uploads\/2015\/03\/roja.png",
         "fanart":"https:\/\/www.stadiotardini.it\/wp-content\/uploads\/2016\/12\/mandrakata.jpg",
         "info":"No info",
         "items":[
            {
               "title":"[COLOR lime]FutbolbogANDRES HQ[\/COLOR] [COLOR aqua](Livestream)[\/COLOR]",
               "link":"https:\/\/www.vivoplay.sigue.la\/p\/bx-3.html",
               "thumbnail":"https:\/\/media.diariorepublica.com\/cms\/wp-content\/uploads\/2015\/03\/roja.png",
               "fanart":"https:\/\/www.stadiotardini.it\/wp-content\/uploads\/2016\/12\/mandrakata.jpg",
               "info":"No info"
            },
            {
               "title":"[COLOR lime]Rivo TVSPORTS 4[\/COLOR] [COLOR aqua](Web (flash))[\/COLOR]",
               "link":"http:\/\/to.xrivonet.info\/4d.html#w",
               "thumbnail":"https:\/\/media.diariorepublica.com\/cms\/wp-content\/uploads\/2015\/03\/roja.png",
               "fanart":"https:\/\/www.stadiotardini.it\/wp-content\/uploads\/2016\/12\/mandrakata.jpg",
               "info":"No info"
            },
            {
               "title":"[COLOR lime]Sebn 19[\/COLOR] [COLOR aqua](Web (flash))[\/COLOR]",
               "link":"http:\/\/sebnsc.club\/180421\/sebn-19.html",
               "thumbnail":"https:\/\/media.diariorepublica.com\/cms\/wp-content\/uploads\/2015\/03\/roja.png",
               "fanart":"https:\/\/www.stadiotardini.it\/wp-content\/uploads\/2016\/12\/mandrakata.jpg",
               "info":"No info"
            },
            {
               "title":"[COLOR lime]My Soccer TV[\/COLOR] [COLOR aqua](Mobile + web flash)[\/COLOR]",
               "link":"https:\/\/mysoccertv.xyz\/ch\/43.php",
               "thumbnail":"https:\/\/media.diariorepublica.com\/cms\/wp-content\/uploads\/2015\/03\/roja.png",
               "fanart":"https:\/\/www.stadiotardini.it\/wp-content\/uploads\/2016\/12\/mandrakata.jpg",
               "info":"No info"
            },
            {
               "title":"[COLOR lime]Lovelystreamer[\/COLOR] [COLOR aqua](Mobile+web flash)[\/COLOR]",
               "link":"https:\/\/extremotvplay.xyz\/18\/NBA-Raptors-Thunder.php",
               "thumbnail":"https:\/\/media.diariorepublica.com\/cms\/wp-content\/uploads\/2015\/03\/roja.png",
               "fanart":"https:\/\/www.stadiotardini.it\/wp-content\/uploads\/2016\/12\/mandrakata.jpg",
               "info":"No info"
            },
            {
               "title":"[COLOR lime]TotalSports[\/COLOR] [COLOR aqua](All devices)[\/COLOR]",
               "link":"http:\/\/totalhdsport.club\/street\/stream19.php",
               "thumbnail":"https:\/\/media.diariorepublica.com\/cms\/wp-content\/uploads\/2015\/03\/roja.png",
               "fanart":"https:\/\/www.stadiotardini.it\/wp-content\/uploads\/2016\/12\/mandrakata.jpg",
               "info":"No info"
            },
            {
               "title":"[COLOR lime]FutbolStream[\/COLOR] [COLOR aqua](All devices)[\/COLOR]",
               "link":"http:\/\/footballstream.pw\/trumm\/st19.php",
               "thumbnail":"https:\/\/media.diariorepublica.com\/cms\/wp-content\/uploads\/2015\/03\/roja.png",
               "fanart":"https:\/\/www.stadiotardini.it\/wp-content\/uploads\/2016\/12\/mandrakata.jpg",
               "info":"No info"
            },
            {
               "title":"[COLOR lime]ZonaSports[\/COLOR] [COLOR aqua](Web(flash))[\/COLOR]",
               "link":"http:\/\/zonasports.xyz\/troga\/stream19.php",
               "thumbnail":"https:\/\/media.diariorepublica.com\/cms\/wp-content\/uploads\/2015\/03\/roja.png",
               "fanart":"https:\/\/www.stadiotardini.it\/wp-content\/uploads\/2016\/12\/mandrakata.jpg",
               "info":"No info"
            },
            {
               "title":"[COLOR lime]britannysports[\/COLOR] [COLOR aqua](Mobile + web flash)[\/COLOR]",
               "link":"https:\/\/britannysports.xyz\/streamb\/43.php",
               "thumbnail":"https:\/\/media.diariorepublica.com\/cms\/wp-content\/uploads\/2015\/03\/roja.png",
               "fanart":"https:\/\/www.stadiotardini.it\/wp-content\/uploads\/2016\/12\/mandrakata.jpg",
               "info":"No info"
            }
         ]
      },
      {
         "name":"[COLOR yellow]2021-04-19 01:00 Calcio[\/COLOR] [COLOR lime]Tampa FC Naples City FC[\/COLOR]",
         "thumbnail":"https:\/\/media.diariorepublica.com\/cms\/wp-content\/uploads\/2015\/03\/roja.png",
         "fanart":"https:\/\/www.stadiotardini.it\/wp-content\/uploads\/2016\/12\/mandrakata.jpg",
         "info":"No info",
         "items":[
            {
               "title":"[COLOR lime]american sports [\/COLOR] [COLOR aqua](Mycujoo)[\/COLOR]",
               "link":"https:\/\/mycujoo.tv\/en\/view\/event\/cknlu1avdbtm90hacgelsybas",
               "thumbnail":"https:\/\/media.diariorepublica.com\/cms\/wp-content\/uploads\/2015\/03\/roja.png",
               "fanart":"https:\/\/www.stadiotardini.it\/wp-content\/uploads\/2016\/12\/mandrakata.jpg",
               "info":"No info"
            }
         ]
      },
      {
         "name":"[COLOR yellow]2021-04-19 01:30 Basket[\/COLOR] [COLOR lime]Mavericks Kings[\/COLOR]",
         "thumbnail":"https:\/\/media.diariorepublica.com\/cms\/wp-content\/uploads\/2015\/03\/roja.png",
         "fanart":"https:\/\/www.stadiotardini.it\/wp-content\/uploads\/2016\/12\/mandrakata.jpg",
         "info":"No info",
         "items":[
            {
               "title":"[COLOR lime]FutbolbogANDRES HQ[\/COLOR] [COLOR aqua](Livestream)[\/COLOR]",
               "link":"https:\/\/www.vivoplay.sigue.la\/p\/bx-4.html",
               "thumbnail":"https:\/\/media.diariorepublica.com\/cms\/wp-content\/uploads\/2015\/03\/roja.png",
               "fanart":"https:\/\/www.stadiotardini.it\/wp-content\/uploads\/2016\/12\/mandrakata.jpg",
               "info":"No info"
            },
            {
               "title":"[COLOR lime]Rivo TVSPORTS 11[\/COLOR] [COLOR aqua](Web (flash))[\/COLOR]",
               "link":"http:\/\/to.xrivonet.info\/nba.html#w",
               "thumbnail":"https:\/\/media.diariorepublica.com\/cms\/wp-content\/uploads\/2015\/03\/roja.png",
               "fanart":"https:\/\/www.stadiotardini.it\/wp-content\/uploads\/2016\/12\/mandrakata.jpg",
               "info":"No info"
            },
            {
               "title":"[COLOR lime]Sebn 20[\/COLOR] [COLOR aqua](Web (flash))[\/COLOR]",
               "link":"http:\/\/sebnsc.club\/180421\/sebn-20.html",
               "thumbnail":"https:\/\/media.diariorepublica.com\/cms\/wp-content\/uploads\/2015\/03\/roja.png",
               "fanart":"https:\/\/www.stadiotardini.it\/wp-content\/uploads\/2016\/12\/mandrakata.jpg",
               "info":"No info"
            },
            {
               "title":"[COLOR lime]My Soccer TV[\/COLOR] [COLOR aqua](Mobile + web flash)[\/COLOR]",
               "link":"https:\/\/mysoccertv.xyz\/ch\/44.php",
               "thumbnail":"https:\/\/media.diariorepublica.com\/cms\/wp-content\/uploads\/2015\/03\/roja.png",
               "fanart":"https:\/\/www.stadiotardini.it\/wp-content\/uploads\/2016\/12\/mandrakata.jpg",
               "info":"No info"
            },
            {
               "title":"[COLOR lime]Lovelystreamer[\/COLOR] [COLOR aqua](Mobile+web flash)[\/COLOR]",
               "link":"https:\/\/extremotvplay.xyz\/18\/NBA-Mavericks-Kings.php",
               "thumbnail":"https:\/\/media.diariorepublica.com\/cms\/wp-content\/uploads\/2015\/03\/roja.png",
               "fanart":"https:\/\/www.stadiotardini.it\/wp-content\/uploads\/2016\/12\/mandrakata.jpg",
               "info":"No info"
            },
            {
               "title":"[COLOR lime]britannysports[\/COLOR] [COLOR aqua](Mobile + web flash)[\/COLOR]",
               "link":"https:\/\/britannysports.xyz\/streamb\/44.php",
               "thumbnail":"https:\/\/media.diariorepublica.com\/cms\/wp-content\/uploads\/2015\/03\/roja.png",
               "fanart":"https:\/\/www.stadiotardini.it\/wp-content\/uploads\/2016\/12\/mandrakata.jpg",
               "info":"No info"
            },
            {
               "title":"[COLOR lime]TotalSports[\/COLOR] [COLOR aqua](Web(flash))[\/COLOR]",
               "link":"http:\/\/totalhdsport.club\/street\/stream20.php",
               "thumbnail":"https:\/\/media.diariorepublica.com\/cms\/wp-content\/uploads\/2015\/03\/roja.png",
               "fanart":"https:\/\/www.stadiotardini.it\/wp-content\/uploads\/2016\/12\/mandrakata.jpg",
               "info":"No info"
            },
            {
               "title":"[COLOR lime]FutbolStream[\/COLOR] [COLOR aqua](All devices)[\/COLOR]",
               "link":"http:\/\/footballstream.pw\/trumm\/st20.php",
               "thumbnail":"https:\/\/media.diariorepublica.com\/cms\/wp-content\/uploads\/2015\/03\/roja.png",
               "fanart":"https:\/\/www.stadiotardini.it\/wp-content\/uploads\/2016\/12\/mandrakata.jpg",
               "info":"No info"
            },
            {
               "title":"[COLOR lime]ZonaSports[\/COLOR] [COLOR aqua](All devices)[\/COLOR]",
               "link":"http:\/\/zonasports.xyz\/troga\/stream20.php",
               "thumbnail":"https:\/\/media.diariorepublica.com\/cms\/wp-content\/uploads\/2015\/03\/roja.png",
               "fanart":"https:\/\/www.stadiotardini.it\/wp-content\/uploads\/2016\/12\/mandrakata.jpg",
               "info":"No info"
            }
         ]
      },
      {
         "name":"[COLOR yellow]2021-04-19 01:30 Calcio[\/COLOR] [COLOR lime]Florida Soccer Soldiers MU Elite FC Red[\/COLOR]",
         "thumbnail":"https:\/\/media.diariorepublica.com\/cms\/wp-content\/uploads\/2015\/03\/roja.png",
         "fanart":"https:\/\/www.stadiotardini.it\/wp-content\/uploads\/2016\/12\/mandrakata.jpg",
         "info":"No info",
         "items":[
            {
               "title":"[COLOR lime]Veter Media[\/COLOR] [COLOR aqua](Mycujoo)[\/COLOR]",
               "link":"https:\/\/mycujoo.tv\/en\/view\/event\/cknjhrnm5auam0g8ecqt3om5t",
               "thumbnail":"https:\/\/media.diariorepublica.com\/cms\/wp-content\/uploads\/2015\/03\/roja.png",
               "fanart":"https:\/\/www.stadiotardini.it\/wp-content\/uploads\/2016\/12\/mandrakata.jpg",
               "info":"No info"
            }
         ]
      },
      {
         "name":"[COLOR yellow]2021-04-19 01:45 Calcio[\/COLOR] [COLOR lime]Irving Rayados Real Irving CD[\/COLOR]",
         "thumbnail":"https:\/\/media.diariorepublica.com\/cms\/wp-content\/uploads\/2015\/03\/roja.png",
         "fanart":"https:\/\/www.stadiotardini.it\/wp-content\/uploads\/2016\/12\/mandrakata.jpg",
         "info":"No info",
         "items":[
            {
               "title":"[COLOR lime]Irving Rayados[\/COLOR] [COLOR aqua](Mycujoo)[\/COLOR]",
               "link":"https:\/\/mycujoo.tv\/en\/view\/event\/cknl8muiwbmxp0g8esz8ql305",
               "thumbnail":"https:\/\/media.diariorepublica.com\/cms\/wp-content\/uploads\/2015\/03\/roja.png",
               "fanart":"https:\/\/www.stadiotardini.it\/wp-content\/uploads\/2016\/12\/mandrakata.jpg",
               "info":"No info"
            }
         ]
      },
      {
         "name":"[COLOR yellow]2021-04-19 02:00 Calcio[\/COLOR] [COLOR lime]Colon Godoy Cruz[\/COLOR]",
         "thumbnail":"https:\/\/media.diariorepublica.com\/cms\/wp-content\/uploads\/2015\/03\/roja.png",
         "fanart":"https:\/\/www.stadiotardini.it\/wp-content\/uploads\/2016\/12\/mandrakata.jpg",
         "info":"No info",
         "items":[
            {
               "title":"[COLOR lime]Rivo PSNTV 11[\/COLOR] [COLOR aqua](Web (flash))[\/COLOR]",
               "link":"http:\/\/to.xrivonet.info\/11c.html#w",
               "thumbnail":"https:\/\/media.diariorepublica.com\/cms\/wp-content\/uploads\/2015\/03\/roja.png",
               "fanart":"https:\/\/www.stadiotardini.it\/wp-content\/uploads\/2016\/12\/mandrakata.jpg",
               "info":"No info"
            },
            {
               "title":"[COLOR lime]Rivo PSNTV 12[\/COLOR] [COLOR aqua](Web (flash))[\/COLOR]",
               "link":"http:\/\/to.xrivonet.info\/11c.html#k3",
               "thumbnail":"https:\/\/media.diariorepublica.com\/cms\/wp-content\/uploads\/2015\/03\/roja.png",
               "fanart":"https:\/\/www.stadiotardini.it\/wp-content\/uploads\/2016\/12\/mandrakata.jpg",
               "info":"No info"
            },
            {
               "title":"[COLOR lime]Sebn 31[\/COLOR] [COLOR aqua](Web (flash))[\/COLOR]",
               "link":"http:\/\/sebnsc.club\/180421\/sebn-31.html",
               "thumbnail":"https:\/\/media.diariorepublica.com\/cms\/wp-content\/uploads\/2015\/03\/roja.png",
               "fanart":"https:\/\/www.stadiotardini.it\/wp-content\/uploads\/2016\/12\/mandrakata.jpg",
               "info":"No info"
            },
            {
               "title":"[COLOR lime]My Soccer TV[\/COLOR] [COLOR aqua](Mobile + web flash)[\/COLOR]",
               "link":"https:\/\/mysoccertv.xyz\/ch\/65.php",
               "thumbnail":"https:\/\/media.diariorepublica.com\/cms\/wp-content\/uploads\/2015\/03\/roja.png",
               "fanart":"https:\/\/www.stadiotardini.it\/wp-content\/uploads\/2016\/12\/mandrakata.jpg",
               "info":"No info"
            },
            {
               "title":"[COLOR lime]Lovelystreamer[\/COLOR] [COLOR aqua](Mobile+web flash)[\/COLOR]",
               "link":"https:\/\/extremotvplay.xyz\/18\/Colon-Godoy-es.php",
               "thumbnail":"https:\/\/media.diariorepublica.com\/cms\/wp-content\/uploads\/2015\/03\/roja.png",
               "fanart":"https:\/\/www.stadiotardini.it\/wp-content\/uploads\/2016\/12\/mandrakata.jpg",
               "info":"No info"
            },
            {
               "title":"[COLOR lime]Athletic Sports[\/COLOR] [COLOR aqua](Web flash)[\/COLOR]",
               "link":"https:\/\/zakkstream.online\/Soccer\/m65.php",
               "thumbnail":"https:\/\/media.diariorepublica.com\/cms\/wp-content\/uploads\/2015\/03\/roja.png",
               "fanart":"https:\/\/www.stadiotardini.it\/wp-content\/uploads\/2016\/12\/mandrakata.jpg",
               "info":"No info"
            },
            {
               "title":"[COLOR lime]P2P Sports[\/COLOR] [COLOR aqua](Web flash + mobile)[\/COLOR]",
               "link":"https:\/\/hikingfly.com\/hiking\/m65.php",
               "thumbnail":"https:\/\/media.diariorepublica.com\/cms\/wp-content\/uploads\/2015\/03\/roja.png",
               "fanart":"https:\/\/www.stadiotardini.it\/wp-content\/uploads\/2016\/12\/mandrakata.jpg",
               "info":"No info"
            },
            {
               "title":"[COLOR lime]Techmaza[\/COLOR] [COLOR aqua](Web flash)[\/COLOR]",
               "link":"https:\/\/techmaza.club\/T15\/65.php",
               "thumbnail":"https:\/\/media.diariorepublica.com\/cms\/wp-content\/uploads\/2015\/03\/roja.png",
               "fanart":"https:\/\/www.stadiotardini.it\/wp-content\/uploads\/2016\/12\/mandrakata.jpg",
               "info":"No info"
            },
            {
               "title":"[COLOR lime]CR7 Soccer[\/COLOR] [COLOR aqua](Web flash)[\/COLOR]",
               "link":"https:\/\/cr7soccer.club\/1004\/M65.php",
               "thumbnail":"https:\/\/media.diariorepublica.com\/cms\/wp-content\/uploads\/2015\/03\/roja.png",
               "fanart":"https:\/\/www.stadiotardini.it\/wp-content\/uploads\/2016\/12\/mandrakata.jpg",
               "info":"No info"
            },
            {
               "title":"[COLOR lime]britannysports[\/COLOR] [COLOR aqua](Mobile + web flash)[\/COLOR]",
               "link":"https:\/\/britannysports.xyz\/streamb\/65.php",
               "thumbnail":"https:\/\/media.diariorepublica.com\/cms\/wp-content\/uploads\/2015\/03\/roja.png",
               "fanart":"https:\/\/www.stadiotardini.it\/wp-content\/uploads\/2016\/12\/mandrakata.jpg",
               "info":"No info"
            }
         ]
      },
      {
         "name":"[COLOR yellow]2021-04-19 02:00 Calcio[\/COLOR] [COLOR lime]Santos Laguna Toluca[\/COLOR]",
         "thumbnail":"https:\/\/media.diariorepublica.com\/cms\/wp-content\/uploads\/2015\/03\/roja.png",
         "fanart":"https:\/\/www.stadiotardini.it\/wp-content\/uploads\/2016\/12\/mandrakata.jpg",
         "info":"No info",
         "items":[
            {
               "title":"[COLOR lime]Rivo PSNTV 1[\/COLOR] [COLOR aqua](Web (flash))[\/COLOR]",
               "link":"http:\/\/to.xrivonet.info\/foxd.html#w",
               "thumbnail":"https:\/\/media.diariorepublica.com\/cms\/wp-content\/uploads\/2015\/03\/roja.png",
               "fanart":"https:\/\/www.stadiotardini.it\/wp-content\/uploads\/2016\/12\/mandrakata.jpg",
               "info":"No info"
            },
            {
               "title":"[COLOR lime]Rivo PSNTV 2[\/COLOR] [COLOR aqua](Web (flash))[\/COLOR]",
               "link":"http:\/\/to.xrivonet.info\/foxd.html#w2",
               "thumbnail":"https:\/\/media.diariorepublica.com\/cms\/wp-content\/uploads\/2015\/03\/roja.png",
               "fanart":"https:\/\/www.stadiotardini.it\/wp-content\/uploads\/2016\/12\/mandrakata.jpg",
               "info":"No info"
            },
            {
               "title":"[COLOR lime]Sebn 17[\/COLOR] [COLOR aqua](Web (flash))[\/COLOR]",
               "link":"http:\/\/sebnsc.club\/180421\/sebn-17.html",
               "thumbnail":"https:\/\/media.diariorepublica.com\/cms\/wp-content\/uploads\/2015\/03\/roja.png",
               "fanart":"https:\/\/www.stadiotardini.it\/wp-content\/uploads\/2016\/12\/mandrakata.jpg",
               "info":"No info"
            },
            {
               "title":"[COLOR lime]My Soccer TV[\/COLOR] [COLOR aqua](Mobile + web flash)[\/COLOR]",
               "link":"https:\/\/mysoccertv.xyz\/ch\/63.php",
               "thumbnail":"https:\/\/media.diariorepublica.com\/cms\/wp-content\/uploads\/2015\/03\/roja.png",
               "fanart":"https:\/\/www.stadiotardini.it\/wp-content\/uploads\/2016\/12\/mandrakata.jpg",
               "info":"No info"
            },
            {
               "title":"[COLOR lime]Lovelystreamer[\/COLOR] [COLOR aqua](Mobile+web flash)[\/COLOR]",
               "link":"https:\/\/extremotvplay.xyz\/18\/Santos-Toluca-es.php",
               "thumbnail":"https:\/\/media.diariorepublica.com\/cms\/wp-content\/uploads\/2015\/03\/roja.png",
               "fanart":"https:\/\/www.stadiotardini.it\/wp-content\/uploads\/2016\/12\/mandrakata.jpg",
               "info":"No info"
            },
            {
               "title":"[COLOR lime]ZONASPORT in HQ 13[\/COLOR] [COLOR aqua](Ustream --)[\/COLOR]",
               "link":"http:\/\/primedeportes.es\/live.php?id=13",
               "thumbnail":"https:\/\/media.diariorepublica.com\/cms\/wp-content\/uploads\/2015\/03\/roja.png",
               "fanart":"https:\/\/www.stadiotardini.it\/wp-content\/uploads\/2016\/12\/mandrakata.jpg",
               "info":"No info"
            },
            {
               "title":"[COLOR lime]ZONASPORT in HQ 01[\/COLOR] [COLOR aqua](Twitch)[\/COLOR]",
               "link":"http:\/\/primedeportes.es\/live.php?id=1",
               "thumbnail":"https:\/\/media.diariorepublica.com\/cms\/wp-content\/uploads\/2015\/03\/roja.png",
               "fanart":"https:\/\/www.stadiotardini.it\/wp-content\/uploads\/2016\/12\/mandrakata.jpg",
               "info":"No info"
            },
            {
               "title":"[COLOR lime]ZONASPORT in HQ 05[\/COLOR] [COLOR aqua](Pc & mobile)[\/COLOR]",
               "link":"http:\/\/primedeportes.es\/live.php?id=5",
               "thumbnail":"https:\/\/media.diariorepublica.com\/cms\/wp-content\/uploads\/2015\/03\/roja.png",
               "fanart":"https:\/\/www.stadiotardini.it\/wp-content\/uploads\/2016\/12\/mandrakata.jpg",
               "info":"No info"
            },
            {
               "title":"[COLOR lime]ZONASPORT in HQ 09[\/COLOR] [COLOR aqua](Pc & mobile)[\/COLOR]",
               "link":"http:\/\/primedeportes.es\/live.php?id=9",
               "thumbnail":"https:\/\/media.diariorepublica.com\/cms\/wp-content\/uploads\/2015\/03\/roja.png",
               "fanart":"https:\/\/www.stadiotardini.it\/wp-content\/uploads\/2016\/12\/mandrakata.jpg",
               "info":"No info"
            },
            {
               "title":"[COLOR lime]ZONASPORT in HQ 11[\/COLOR] [COLOR aqua](Pc & mobile)[\/COLOR]",
               "link":"http:\/\/primedeportes.es\/live.php?id=11",
               "thumbnail":"https:\/\/media.diariorepublica.com\/cms\/wp-content\/uploads\/2015\/03\/roja.png",
               "fanart":"https:\/\/www.stadiotardini.it\/wp-content\/uploads\/2016\/12\/mandrakata.jpg",
               "info":"No info"
            },
            {
               "title":"[COLOR lime]Athletic Sports[\/COLOR] [COLOR aqua](Web flash)[\/COLOR]",
               "link":"https:\/\/zakkstream.online\/Soccer\/s6.php",
               "thumbnail":"https:\/\/media.diariorepublica.com\/cms\/wp-content\/uploads\/2015\/03\/roja.png",
               "fanart":"https:\/\/www.stadiotardini.it\/wp-content\/uploads\/2016\/12\/mandrakata.jpg",
               "info":"No info"
            },
            {
               "title":"[COLOR lime]Athletic Sports[\/COLOR] [COLOR aqua](Web flash)[\/COLOR]",
               "link":"https:\/\/zakkstream.online\/Soccer\/m63.php",
               "thumbnail":"https:\/\/media.diariorepublica.com\/cms\/wp-content\/uploads\/2015\/03\/roja.png",
               "fanart":"https:\/\/www.stadiotardini.it\/wp-content\/uploads\/2016\/12\/mandrakata.jpg",
               "info":"No info"
            },
            {
               "title":"[COLOR lime]My Soccer TV[\/COLOR] [COLOR aqua](Mobile + web flash)[\/COLOR]",
               "link":"https:\/\/mysoccertv.xyz\/sp\/s6.php",
               "thumbnail":"https:\/\/media.diariorepublica.com\/cms\/wp-content\/uploads\/2015\/03\/roja.png",
               "fanart":"https:\/\/www.stadiotardini.it\/wp-content\/uploads\/2016\/12\/mandrakata.jpg",
               "info":"No info"
            },
            {
               "title":"[COLOR lime]P2P Sports[\/COLOR] [COLOR aqua](Web flash + mobile)[\/COLOR]",
               "link":"https:\/\/hikingfly.com\/hiking\/m63.php",
               "thumbnail":"https:\/\/media.diariorepublica.com\/cms\/wp-content\/uploads\/2015\/03\/roja.png",
               "fanart":"https:\/\/www.stadiotardini.it\/wp-content\/uploads\/2016\/12\/mandrakata.jpg",
               "info":"No info"
            },
            {
               "title":"[COLOR lime]Techmaza[\/COLOR] [COLOR aqua](Web flash)[\/COLOR]",
               "link":"https:\/\/techmaza.club\/T15\/63.php",
               "thumbnail":"https:\/\/media.diariorepublica.com\/cms\/wp-content\/uploads\/2015\/03\/roja.png",
               "fanart":"https:\/\/www.stadiotardini.it\/wp-content\/uploads\/2016\/12\/mandrakata.jpg",
               "info":"No info"
            },
            {
               "title":"[COLOR lime]CR7 Soccer[\/COLOR] [COLOR aqua](Web flash)[\/COLOR]",
               "link":"https:\/\/cr7soccer.club\/1004\/6.php",
               "thumbnail":"https:\/\/media.diariorepublica.com\/cms\/wp-content\/uploads\/2015\/03\/roja.png",
               "fanart":"https:\/\/www.stadiotardini.it\/wp-content\/uploads\/2016\/12\/mandrakata.jpg",
               "info":"No info"
            },
            {
               "title":"[COLOR lime]britannysports[\/COLOR] [COLOR aqua](Mobile + web flash)[\/COLOR]",
               "link":"https:\/\/britannysports.xyz\/streamb\/63.php",
               "thumbnail":"https:\/\/media.diariorepublica.com\/cms\/wp-content\/uploads\/2015\/03\/roja.png",
               "fanart":"https:\/\/www.stadiotardini.it\/wp-content\/uploads\/2016\/12\/mandrakata.jpg",
               "info":"No info"
            },
            {
               "title":"[COLOR lime]TotalSports[\/COLOR] [COLOR aqua](Web(flash))[\/COLOR]",
               "link":"http:\/\/totalhdsport.club\/street\/stream17.php",
               "thumbnail":"https:\/\/media.diariorepublica.com\/cms\/wp-content\/uploads\/2015\/03\/roja.png",
               "fanart":"https:\/\/www.stadiotardini.it\/wp-content\/uploads\/2016\/12\/mandrakata.jpg",
               "info":"No info"
            },
            {
               "title":"[COLOR lime]FutbolStream[\/COLOR] [COLOR aqua](All devices)[\/COLOR]",
               "link":"http:\/\/footballstream.pw\/trumm\/st17.php",
               "thumbnail":"https:\/\/media.diariorepublica.com\/cms\/wp-content\/uploads\/2015\/03\/roja.png",
               "fanart":"https:\/\/www.stadiotardini.it\/wp-content\/uploads\/2016\/12\/mandrakata.jpg",
               "info":"No info"
            },
            {
               "title":"[COLOR lime]ZonaTV[\/COLOR] [COLOR aqua](All devices)[\/COLOR]",
               "link":"http:\/\/zonasports.xyz\/troga\/stream17.php",
               "thumbnail":"https:\/\/media.diariorepublica.com\/cms\/wp-content\/uploads\/2015\/03\/roja.png",
               "fanart":"https:\/\/www.stadiotardini.it\/wp-content\/uploads\/2016\/12\/mandrakata.jpg",
               "info":"No info"
            }
         ]
      },
      {
         "name":"[COLOR yellow]2021-04-19 02:00 Calcio[\/COLOR] [COLOR lime]Merced United Acoreano Sport[\/COLOR]",
         "thumbnail":"https:\/\/media.diariorepublica.com\/cms\/wp-content\/uploads\/2015\/03\/roja.png",
         "fanart":"https:\/\/www.stadiotardini.it\/wp-content\/uploads\/2016\/12\/mandrakata.jpg",
         "info":"No info",
         "items":[
            {
               "title":"[COLOR lime]Merced United[\/COLOR] [COLOR aqua](Mycujoo)[\/COLOR]",
               "link":"https:\/\/mycujoo.tv\/en\/view\/event\/ckn3ovhfs3kkc0g8epzs86zmd",
               "thumbnail":"https:\/\/media.diariorepublica.com\/cms\/wp-content\/uploads\/2015\/03\/roja.png",
               "fanart":"https:\/\/www.stadiotardini.it\/wp-content\/uploads\/2016\/12\/mandrakata.jpg",
               "info":"No info"
            }
         ]
      },
      {
         "name":"[COLOR yellow]2021-04-19 02:00 Calcio[\/COLOR] [COLOR lime]SC Verdugos Rose City FC[\/COLOR]",
         "thumbnail":"https:\/\/media.diariorepublica.com\/cms\/wp-content\/uploads\/2015\/03\/roja.png",
         "fanart":"https:\/\/www.stadiotardini.it\/wp-content\/uploads\/2016\/12\/mandrakata.jpg",
         "info":"No info",
         "items":[
            {
               "title":"[COLOR lime]Sporting Club [\/COLOR] [COLOR aqua](Mycujoo)[\/COLOR]",
               "link":"https:\/\/mycujoo.tv\/en\/view\/event\/cknjfmlqxat9n0g8e52nc2ye4",
               "thumbnail":"https:\/\/media.diariorepublica.com\/cms\/wp-content\/uploads\/2015\/03\/roja.png",
               "fanart":"https:\/\/www.stadiotardini.it\/wp-content\/uploads\/2016\/12\/mandrakata.jpg",
               "info":"No info"
            }
         ]
      },
      {
         "name":"[COLOR yellow]2021-04-19 03:00 Calcio[\/COLOR] [COLOR lime]Fullerton Disciples FC Santa Ana Winds FC[\/COLOR]",
         "thumbnail":"https:\/\/media.diariorepublica.com\/cms\/wp-content\/uploads\/2015\/03\/roja.png",
         "fanart":"https:\/\/www.stadiotardini.it\/wp-content\/uploads\/2016\/12\/mandrakata.jpg",
         "info":"No info",
         "items":[
            {
               "title":"[COLOR lime]Disciples FC[\/COLOR] [COLOR aqua](Mycujoo)[\/COLOR]",
               "link":"https:\/\/mycujoo.tv\/en\/view\/event\/cknm7i91gc72z0ibmf9d57s52",
               "thumbnail":"https:\/\/media.diariorepublica.com\/cms\/wp-content\/uploads\/2015\/03\/roja.png",
               "fanart":"https:\/\/www.stadiotardini.it\/wp-content\/uploads\/2016\/12\/mandrakata.jpg",
               "info":"No info"
            }
         ]
      },
      {
         "name":"[COLOR yellow]2021-04-19 04:00 Calcio[\/COLOR] [COLOR lime]Vancouver Whitecaps Portland Timbers[\/COLOR]",
         "thumbnail":"https:\/\/media.diariorepublica.com\/cms\/wp-content\/uploads\/2015\/03\/roja.png",
         "fanart":"https:\/\/www.stadiotardini.it\/wp-content\/uploads\/2016\/12\/mandrakata.jpg",
         "info":"No info",
         "items":[
            {
               "title":"[COLOR lime]Rivo PSNTV 2[\/COLOR] [COLOR aqua](Web (flash))[\/COLOR]",
               "link":"http:\/\/to.xrivonet.info\/ad2.html#w",
               "thumbnail":"https:\/\/media.diariorepublica.com\/cms\/wp-content\/uploads\/2015\/03\/roja.png",
               "fanart":"https:\/\/www.stadiotardini.it\/wp-content\/uploads\/2016\/12\/mandrakata.jpg",
               "info":"No info"
            },
            {
               "title":"[COLOR lime]Sebn 29[\/COLOR] [COLOR aqua](Web (flash))[\/COLOR]",
               "link":"http:\/\/sebnsc.club\/180421\/sebn-29.html",
               "thumbnail":"https:\/\/media.diariorepublica.com\/cms\/wp-content\/uploads\/2015\/03\/roja.png",
               "fanart":"https:\/\/www.stadiotardini.it\/wp-content\/uploads\/2016\/12\/mandrakata.jpg",
               "info":"No info"
            },
            {
               "title":"[COLOR lime]My Soccer TV[\/COLOR] [COLOR aqua](Mobile + web flash)[\/COLOR]",
               "link":"https:\/\/mysoccertv.xyz\/ch\/23.php",
               "thumbnail":"https:\/\/media.diariorepublica.com\/cms\/wp-content\/uploads\/2015\/03\/roja.png",
               "fanart":"https:\/\/www.stadiotardini.it\/wp-content\/uploads\/2016\/12\/mandrakata.jpg",
               "info":"No info"
            },
            {
               "title":"[COLOR lime]Techmaza[\/COLOR] [COLOR aqua](Web flash)[\/COLOR]",
               "link":"https:\/\/techmaza.club\/T15\/23.php",
               "thumbnail":"https:\/\/media.diariorepublica.com\/cms\/wp-content\/uploads\/2015\/03\/roja.png",
               "fanart":"https:\/\/www.stadiotardini.it\/wp-content\/uploads\/2016\/12\/mandrakata.jpg",
               "info":"No info"
            },
            {
               "title":"[COLOR lime]CR7 Soccer[\/COLOR] [COLOR aqua](Web flash)[\/COLOR]",
               "link":"https:\/\/cr7soccer.club\/1004\/2.php",
               "thumbnail":"https:\/\/media.diariorepublica.com\/cms\/wp-content\/uploads\/2015\/03\/roja.png",
               "fanart":"https:\/\/www.stadiotardini.it\/wp-content\/uploads\/2016\/12\/mandrakata.jpg",
               "info":"No info"
            },
            {
               "title":"[COLOR lime]britannysports[\/COLOR] [COLOR aqua](Mobile + web flash)[\/COLOR]",
               "link":"https:\/\/britannysports.xyz\/streamb\/23.php",
               "thumbnail":"https:\/\/media.diariorepublica.com\/cms\/wp-content\/uploads\/2015\/03\/roja.png",
               "fanart":"https:\/\/www.stadiotardini.it\/wp-content\/uploads\/2016\/12\/mandrakata.jpg",
               "info":"No info"
            },
            {
               "title":"[COLOR lime]Lovelystreamer[\/COLOR] [COLOR aqua](Mobile+web flash)[\/COLOR]",
               "link":"https:\/\/extremotvplay.xyz\/18\/Vancouver-Whitecaps-Portland.php",
               "thumbnail":"https:\/\/media.diariorepublica.com\/cms\/wp-content\/uploads\/2015\/03\/roja.png",
               "fanart":"https:\/\/www.stadiotardini.it\/wp-content\/uploads\/2016\/12\/mandrakata.jpg",
               "info":"No info"
            },
            {
               "title":"[COLOR lime]TotalSports[\/COLOR] [COLOR aqua](Web(flash))[\/COLOR]",
               "link":"http:\/\/totalhdsport.club\/street\/stream29.php",
               "thumbnail":"https:\/\/media.diariorepublica.com\/cms\/wp-content\/uploads\/2015\/03\/roja.png",
               "fanart":"https:\/\/www.stadiotardini.it\/wp-content\/uploads\/2016\/12\/mandrakata.jpg",
               "info":"No info"
            },
            {
               "title":"[COLOR lime]FutbolStream[\/COLOR] [COLOR aqua](All devices)[\/COLOR]",
               "link":"http:\/\/footballstream.pw\/trumm\/st29.php",
               "thumbnail":"https:\/\/media.diariorepublica.com\/cms\/wp-content\/uploads\/2015\/03\/roja.png",
               "fanart":"https:\/\/www.stadiotardini.it\/wp-content\/uploads\/2016\/12\/mandrakata.jpg",
               "info":"No info"
            },
            {
               "title":"[COLOR lime]ZonaSports[\/COLOR] [COLOR aqua](All devices)[\/COLOR]",
               "link":"http:\/\/zonasports.xyz\/troga\/stream29.php",
               "thumbnail":"https:\/\/media.diariorepublica.com\/cms\/wp-content\/uploads\/2015\/03\/roja.png",
               "fanart":"https:\/\/www.stadiotardini.it\/wp-content\/uploads\/2016\/12\/mandrakata.jpg",
               "info":"No info"
            }
         ]
      },
      {
         "name":"[COLOR yellow]2021-04-19 04:00 Basket[\/COLOR] [COLOR lime]Clippers Timberwolves[\/COLOR]",
         "thumbnail":"https:\/\/media.diariorepublica.com\/cms\/wp-content\/uploads\/2015\/03\/roja.png",
         "fanart":"https:\/\/www.stadiotardini.it\/wp-content\/uploads\/2016\/12\/mandrakata.jpg",
         "info":"No info",
         "items":[
            {
               "title":"[COLOR lime]Rivo TVSPORTS 11[\/COLOR] [COLOR aqua](Web (flash))[\/COLOR]",
               "link":"http:\/\/to.xrivonet.info\/nba.html#w",
               "thumbnail":"https:\/\/media.diariorepublica.com\/cms\/wp-content\/uploads\/2015\/03\/roja.png",
               "fanart":"https:\/\/www.stadiotardini.it\/wp-content\/uploads\/2016\/12\/mandrakata.jpg",
               "info":"No info"
            },
            {
               "title":"[COLOR lime]Sebn 21[\/COLOR] [COLOR aqua](Web (flash))[\/COLOR]",
               "link":"http:\/\/sebnsc.club\/180421\/sebn-21.html",
               "thumbnail":"https:\/\/media.diariorepublica.com\/cms\/wp-content\/uploads\/2015\/03\/roja.png",
               "fanart":"https:\/\/www.stadiotardini.it\/wp-content\/uploads\/2016\/12\/mandrakata.jpg",
               "info":"No info"
            },
            {
               "title":"[COLOR lime]My Soccer TV[\/COLOR] [COLOR aqua](Mobile + web flash)[\/COLOR]",
               "link":"https:\/\/mysoccertv.xyz\/ch\/45.php",
               "thumbnail":"https:\/\/media.diariorepublica.com\/cms\/wp-content\/uploads\/2015\/03\/roja.png",
               "fanart":"https:\/\/www.stadiotardini.it\/wp-content\/uploads\/2016\/12\/mandrakata.jpg",
               "info":"No info"
            },
            {
               "title":"[COLOR lime]britannysports[\/COLOR] [COLOR aqua](Mobile + web flash)[\/COLOR]",
               "link":"https:\/\/britannysports.xyz\/streamb\/45.php",
               "thumbnail":"https:\/\/media.diariorepublica.com\/cms\/wp-content\/uploads\/2015\/03\/roja.png",
               "fanart":"https:\/\/www.stadiotardini.it\/wp-content\/uploads\/2016\/12\/mandrakata.jpg",
               "info":"No info"
            },
            {
               "title":"[COLOR lime]Lovelystreamer[\/COLOR] [COLOR aqua](Mobile+web flash)[\/COLOR]",
               "link":"https:\/\/extremotvplay.xyz\/18\/NBA-Clippers-Timberwolves.php",
               "thumbnail":"https:\/\/media.diariorepublica.com\/cms\/wp-content\/uploads\/2015\/03\/roja.png",
               "fanart":"https:\/\/www.stadiotardini.it\/wp-content\/uploads\/2016\/12\/mandrakata.jpg",
               "info":"No info"
            },
            {
               "title":"[COLOR lime]TotalSports[\/COLOR] [COLOR aqua](Web(flash))[\/COLOR]",
               "link":"http:\/\/totalhdsport.club\/street\/stream21.php",
               "thumbnail":"https:\/\/media.diariorepublica.com\/cms\/wp-content\/uploads\/2015\/03\/roja.png",
               "fanart":"https:\/\/www.stadiotardini.it\/wp-content\/uploads\/2016\/12\/mandrakata.jpg",
               "info":"No info"
            },
            {
               "title":"[COLOR lime]FutbolStream[\/COLOR] [COLOR aqua](All devices)[\/COLOR]",
               "link":"http:\/\/footballstream.pw\/trumm\/st21.php",
               "thumbnail":"https:\/\/media.diariorepublica.com\/cms\/wp-content\/uploads\/2015\/03\/roja.png",
               "fanart":"https:\/\/www.stadiotardini.it\/wp-content\/uploads\/2016\/12\/mandrakata.jpg",
               "info":"No info"
            },
            {
               "title":"[COLOR lime]ZonaSports[\/COLOR] [COLOR aqua](All devices)[\/COLOR]",
               "link":"http:\/\/zonasports.xyz\/troga\/stream21.php",
               "thumbnail":"https:\/\/media.diariorepublica.com\/cms\/wp-content\/uploads\/2015\/03\/roja.png",
               "fanart":"https:\/\/www.stadiotardini.it\/wp-content\/uploads\/2016\/12\/mandrakata.jpg",
               "info":"No info"
            }
         ]
      },
      {
         "name":"[COLOR yellow]2021-04-19 04:06 Calcio[\/COLOR] [COLOR lime]Monterrey Pachuca[\/COLOR]",
         "thumbnail":"https:\/\/media.diariorepublica.com\/cms\/wp-content\/uploads\/2015\/03\/roja.png",
         "fanart":"https:\/\/www.stadiotardini.it\/wp-content\/uploads\/2016\/12\/mandrakata.jpg",
         "info":"No info",
         "items":[
            {
               "title":"[COLOR lime]Rivo PSNTV 1[\/COLOR] [COLOR aqua](Web (flash))[\/COLOR]",
               "link":"http:\/\/to.xrivonet.info\/foxd.html#w",
               "thumbnail":"https:\/\/media.diariorepublica.com\/cms\/wp-content\/uploads\/2015\/03\/roja.png",
               "fanart":"https:\/\/www.stadiotardini.it\/wp-content\/uploads\/2016\/12\/mandrakata.jpg",
               "info":"No info"
            },
            {
               "title":"[COLOR lime]Rivo PSNTV 2[\/COLOR] [COLOR aqua](Web (flash))[\/COLOR]",
               "link":"http:\/\/to.xrivonet.info\/foxd.html#w2",
               "thumbnail":"https:\/\/media.diariorepublica.com\/cms\/wp-content\/uploads\/2015\/03\/roja.png",
               "fanart":"https:\/\/www.stadiotardini.it\/wp-content\/uploads\/2016\/12\/mandrakata.jpg",
               "info":"No info"
            },
            {
               "title":"[COLOR lime]Sebn 17[\/COLOR] [COLOR aqua](Web (flash))[\/COLOR]",
               "link":"http:\/\/sebnsc.club\/180421\/sebn-17.html",
               "thumbnail":"https:\/\/media.diariorepublica.com\/cms\/wp-content\/uploads\/2015\/03\/roja.png",
               "fanart":"https:\/\/www.stadiotardini.it\/wp-content\/uploads\/2016\/12\/mandrakata.jpg",
               "info":"No info"
            },
            {
               "title":"[COLOR lime]My Soccer TV[\/COLOR] [COLOR aqua](Mobile + web flash)[\/COLOR]",
               "link":"https:\/\/mysoccertv.xyz\/ch\/63.php",
               "thumbnail":"https:\/\/media.diariorepublica.com\/cms\/wp-content\/uploads\/2015\/03\/roja.png",
               "fanart":"https:\/\/www.stadiotardini.it\/wp-content\/uploads\/2016\/12\/mandrakata.jpg",
               "info":"No info"
            },
            {
               "title":"[COLOR lime]ZONASPORT in HQ 13[\/COLOR] [COLOR aqua](Ustream --)[\/COLOR]",
               "link":"http:\/\/primedeportes.es\/live.php?id=13",
               "thumbnail":"https:\/\/media.diariorepublica.com\/cms\/wp-content\/uploads\/2015\/03\/roja.png",
               "fanart":"https:\/\/www.stadiotardini.it\/wp-content\/uploads\/2016\/12\/mandrakata.jpg",
               "info":"No info"
            },
            {
               "title":"[COLOR lime]ZONASPORT in HQ 01[\/COLOR] [COLOR aqua](Twitch)[\/COLOR]",
               "link":"http:\/\/primedeportes.es\/live.php?id=1",
               "thumbnail":"https:\/\/media.diariorepublica.com\/cms\/wp-content\/uploads\/2015\/03\/roja.png",
               "fanart":"https:\/\/www.stadiotardini.it\/wp-content\/uploads\/2016\/12\/mandrakata.jpg",
               "info":"No info"
            },
            {
               "title":"[COLOR lime]ZONASPORT in HQ 05[\/COLOR] [COLOR aqua](Pc & mobile)[\/COLOR]",
               "link":"http:\/\/primedeportes.es\/live.php?id=5",
               "thumbnail":"https:\/\/media.diariorepublica.com\/cms\/wp-content\/uploads\/2015\/03\/roja.png",
               "fanart":"https:\/\/www.stadiotardini.it\/wp-content\/uploads\/2016\/12\/mandrakata.jpg",
               "info":"No info"
            },
            {
               "title":"[COLOR lime]ZONASPORT in HQ 09[\/COLOR] [COLOR aqua](Pc & mobile)[\/COLOR]",
               "link":"http:\/\/primedeportes.es\/live.php?id=9",
               "thumbnail":"https:\/\/media.diariorepublica.com\/cms\/wp-content\/uploads\/2015\/03\/roja.png",
               "fanart":"https:\/\/www.stadiotardini.it\/wp-content\/uploads\/2016\/12\/mandrakata.jpg",
               "info":"No info"
            },
            {
               "title":"[COLOR lime]ZONASPORT in HQ 11[\/COLOR] [COLOR aqua](Pc & mobile)[\/COLOR]",
               "link":"http:\/\/primedeportes.es\/live.php?id=11",
               "thumbnail":"https:\/\/media.diariorepublica.com\/cms\/wp-content\/uploads\/2015\/03\/roja.png",
               "fanart":"https:\/\/www.stadiotardini.it\/wp-content\/uploads\/2016\/12\/mandrakata.jpg",
               "info":"No info"
            },
            {
               "title":"[COLOR lime]Techmaza[\/COLOR] [COLOR aqua](Web flash)[\/COLOR]",
               "link":"https:\/\/techmaza.club\/T15\/63.php",
               "thumbnail":"https:\/\/media.diariorepublica.com\/cms\/wp-content\/uploads\/2015\/03\/roja.png",
               "fanart":"https:\/\/www.stadiotardini.it\/wp-content\/uploads\/2016\/12\/mandrakata.jpg",
               "info":"No info"
            },
            {
               "title":"[COLOR lime]CR7 Soccer[\/COLOR] [COLOR aqua](Web flash)[\/COLOR]",
               "link":"https:\/\/cr7soccer.club\/1004\/6.php",
               "thumbnail":"https:\/\/media.diariorepublica.com\/cms\/wp-content\/uploads\/2015\/03\/roja.png",
               "fanart":"https:\/\/www.stadiotardini.it\/wp-content\/uploads\/2016\/12\/mandrakata.jpg",
               "info":"No info"
            },
            {
               "title":"[COLOR lime]britannysports[\/COLOR] [COLOR aqua](Mobile + web flash)[\/COLOR]",
               "link":"https:\/\/britannysports.xyz\/streamb\/63.php",
               "thumbnail":"https:\/\/media.diariorepublica.com\/cms\/wp-content\/uploads\/2015\/03\/roja.png",
               "fanart":"https:\/\/www.stadiotardini.it\/wp-content\/uploads\/2016\/12\/mandrakata.jpg",
               "info":"No info"
            },
            {
               "title":"[COLOR lime]Lovelystreamer[\/COLOR] [COLOR aqua](Mobile+web flash)[\/COLOR]",
               "link":"https:\/\/extremotvplay.xyz\/18\/Monterrey-Pachuca-es.php",
               "thumbnail":"https:\/\/media.diariorepublica.com\/cms\/wp-content\/uploads\/2015\/03\/roja.png",
               "fanart":"https:\/\/www.stadiotardini.it\/wp-content\/uploads\/2016\/12\/mandrakata.jpg",
               "info":"No info"
            }
         ]
      },
      {
         "name":"[COLOR yellow]2021-04-19 05:00 Calcio[\/COLOR] [COLOR lime]Irvine FC CF Cachorros[\/COLOR]",
         "thumbnail":"https:\/\/media.diariorepublica.com\/cms\/wp-content\/uploads\/2015\/03\/roja.png",
         "fanart":"https:\/\/www.stadiotardini.it\/wp-content\/uploads\/2016\/12\/mandrakata.jpg",
         "info":"No info",
         "items":[
            {
               "title":"[COLOR lime]Irvine FC[\/COLOR] [COLOR aqua](Mycujoo)[\/COLOR]",
               "link":"https:\/\/mycujoo.tv\/en\/view\/event\/cknkv1powbc0u0hacsa68z7j3",
               "thumbnail":"https:\/\/media.diariorepublica.com\/cms\/wp-content\/uploads\/2015\/03\/roja.png",
               "fanart":"https:\/\/www.stadiotardini.it\/wp-content\/uploads\/2016\/12\/mandrakata.jpg",
               "info":"No info"
            }
         ]
      },
      {
         "name":"[COLOR yellow]2021-04-19 07:30 Nuoto New Zealand Age Group Championships[\/COLOR] [COLOR lime]Session Two[\/COLOR]",
         "thumbnail":"https:\/\/media.diariorepublica.com\/cms\/wp-content\/uploads\/2015\/03\/roja.png",
         "fanart":"https:\/\/www.stadiotardini.it\/wp-content\/uploads\/2016\/12\/mandrakata.jpg",
         "info":"No info",
         "items":[
            {
               "title":"[COLOR lime]Sky Sports Next NZ[\/COLOR] [COLOR aqua](Youtube --)[\/COLOR]",
               "link":"https:\/\/www.youtube-nocookie.com\/embed\/CqCSkfxbmkk?autoplay=1",
               "thumbnail":"https:\/\/media.diariorepublica.com\/cms\/wp-content\/uploads\/2015\/03\/roja.png",
               "fanart":"https:\/\/www.stadiotardini.it\/wp-content\/uploads\/2016\/12\/mandrakata.jpg",
               "info":"No info"
            }
         ]
      },
      {
         "name":"[COLOR yellow]2021-04-19 13:00 Calcio[\/COLOR] [COLOR lime]Wolverhampton Wanderers FC West Bromwich Albion[\/COLOR]",
         "thumbnail":"https:\/\/media.diariorepublica.com\/cms\/wp-content\/uploads\/2015\/03\/roja.png",
         "fanart":"https:\/\/www.stadiotardini.it\/wp-content\/uploads\/2016\/12\/mandrakata.jpg",
         "info":"No info",
         "items":[
            {
               "title":"[COLOR lime]PPTV China only[\/COLOR] [COLOR aqua](Flash)[\/COLOR]",
               "link":"http:\/\/sports.pptv.com\/sportslive?sectionid=184549&from=pptv",
               "thumbnail":"https:\/\/media.diariorepublica.com\/cms\/wp-content\/uploads\/2015\/03\/roja.png",
               "fanart":"https:\/\/www.stadiotardini.it\/wp-content\/uploads\/2016\/12\/mandrakata.jpg",
               "info":"No info"
            }
         ]
      }
   ]
}